tabstruct/__init__.py
tabstruct/common/__init__.py
tabstruct/common/data/DataHelper.py
tabstruct/common/data/DataModule.py
tabstruct/common/data/__init__.py
tabstruct/common/model/BaseModel.py
tabstruct/common/model/BaseModelHelper.py
tabstruct/common/runtime/config/__init__.py
tabstruct/common/runtime/config/argument.py
tabstruct/common/runtime/config/env.py
tabstruct/common/runtime/error/ManualStopError.py
tabstruct/common/runtime/error/__init__.py
tabstruct/common/runtime/log/FileHelper.py
tabstruct/common/runtime/log/TerminalIO.py
tabstruct/common/runtime/log/WandbHelper.py
tabstruct/common/runtime/log/__init__.py
tabstruct/experiment/__init__.py
tabstruct/experiment/run_experiment.py
tabstruct/experiment/pipeline/BasePipeline.py
tabstruct/experiment/pipeline/PipelineHelper.py
tabstruct/experiment/pipeline/__init__.py
tabstruct/experiment/pipeline/utils/GenerationPipeline.py
tabstruct/experiment/pipeline/utils/PredictionPipeline.py
tabstruct/experiment/pipeline/utils/__init__.py
tabstruct/experiment/tune/BaseTuner.py
tabstruct/experiment/tune/TunerHelper.py
tabstruct/experiment/tune/__init__.py
tabstruct/generation/__init__.py
tabstruct/generation/models/BaseGenerator.py
tabstruct/generation/models/GeneratorHelper.py
tabstruct/generation/models/__init__.py
tabstruct/generation/models/imblearn/SMOTE.py
tabstruct/generation/models/imblearn/__init__.py
tabstruct/generation/models/synth/ARF.py
tabstruct/generation/models/synth/BN.py
tabstruct/generation/models/synth/CTGAN.py
tabstruct/generation/models/synth/GOGGLE.py
tabstruct/generation/models/synth/GReaT.py
tabstruct/generation/models/synth/NFLOW.py
tabstruct/generation/models/synth/SCM.py
tabstruct/generation/models/synth/TVAE.py
tabstruct/generation/models/synth/TabDDPM.py
tabstruct/generation/models/synth/__init__.py
tabstruct/generation/models/utils/__init__.py
tabstruct/generation/models/utils/evaluation.py
tabstruct/generation/notebooks/mini_usecase/cd_mixed_data.ipynb
tabstruct-2025.8.7.dist-info/METADATA
tabstruct-2025.8.7.dist-info/WHEEL
tabstruct-2025.8.7.dist-info/licenses/LICENSE
tabstruct-2025.8.7.dist-info/RECORD
