Metadata-Version: 2.4
Name: tabstruct
Version: 2025.8.7
Summary: A Python project framework for managing dual-repository workflows with automated release management and development tools
Author-email: Xiangjian Jiang <silencejiang12138@gmail.com>
License:                                  Apache License
License-File: LICENSE
Keywords: automation,development,framework,repository,template
Classifier: License :: OSI Approved :: Apache Software License
Classifier: Programming Language :: Python :: 3
Classifier: Programming Language :: Python :: 3.10
Requires-Python: >=3.10
Requires-Dist: autogluon
Requires-Dist: bnlearn
Requires-Dist: build
Requires-Dist: causal-learn
Requires-Dist: cleanlab
Requires-Dist: flake8
Requires-Dist: hatchling
Requires-Dist: httplib2
Requires-Dist: ipykernel
Requires-Dist: lightning-utilities==0.14.3
Requires-Dist: lightning==2.5.2
Requires-Dist: mostlyai-qa
Requires-Dist: myst-parser
Requires-Dist: nbconvert
Requires-Dist: pgmpy==1.0.0
Requires-Dist: pylint
Requires-Dist: pytest
Requires-Dist: rich==13.9.4
Requires-Dist: rtdl-revisiting-models
Requires-Dist: sdmetrics
Requires-Dist: seaborn
Requires-Dist: setuptools==75.1.0
Requires-Dist: sphinx
Requires-Dist: sphinx-book-theme
Requires-Dist: sphinx-rtd-theme
Requires-Dist: tabcamel==2025.8.10
Requires-Dist: tabeval[all]==2025.8.10
Requires-Dist: tabpfn
Requires-Dist: thop
Requires-Dist: ucimlrepo
Requires-Dist: wandb==0.18.7
Requires-Dist: wrapt-timeout-decorator
Provides-Extra: dev
